wacryptolib/__init__.py
wacryptolib/__main__.py
wacryptolib/_crypto_backend/__init__.py
wacryptolib/_crypto_backend/pycryptodome.py
wacryptolib/authdevice.py
wacryptolib/authenticator.py
wacryptolib/cipher.py
wacryptolib/cli.py
wacryptolib/cryptainer.py
wacryptolib/error_handling.py
wacryptolib/exceptions.py
wacryptolib/jsonrpc_client.py
wacryptolib/keygen.py
wacryptolib/keystore.py
wacryptolib/operations.py
wacryptolib/scaffolding.py
wacryptolib/sensor.py
wacryptolib/shared_secret.py
wacryptolib/signature.py
wacryptolib/trustee.py
wacryptolib/utilities.py
wacryptolib-0.11.dist-info/entry_points.txt
wacryptolib-0.11.dist-info/License.txt
wacryptolib-0.11.dist-info/METADATA
wacryptolib-0.11.dist-info/WHEEL
wacryptolib-0.11.dist-info/RECORD
